python_bring_api/__init__.py
python_bring_api/bring.py
python_bring_api/exceptions.py
python_bring_api/types.py
python_bring_api-3.0.0.dist-info/LICENSE
python_bring_api-3.0.0.dist-info/METADATA
python_bring_api-3.0.0.dist-info/WHEEL
python_bring_api-3.0.0.dist-info/top_level.txt
python_bring_api-3.0.0.dist-info/RECORD
