Metadata-Version: 2.1
Name: python-bring-api
Version: 3.0.0
Summary: Unofficial python package to access Bring! shopping lists API.
Home-page: https://github.com/blue1stone/python-bring-api
Author: Elias Ball
Author-email: contact.eliasball@gmail.com
Classifier: Programming Language :: Python :: 3
Classifier: License :: OSI Approved :: MIT License
Classifier: Operating System :: OS Independent
Requires-Python: >=3.8
License-File: LICENSE
Requires-Dist: aiohttp
